README.txt
setup.py
conf/__init__.py
conf/ch.py
conf/common.py
conf/common_tests.py
conf/dbupdate.py
fitbit_conf.egg-info/PKG-INFO
fitbit_conf.egg-info/SOURCES.txt
fitbit_conf.egg-info/dependency_links.txt
fitbit_conf.egg-info/entry_points.txt
fitbit_conf.egg-info/top_level.txt