Metadata-Version: 1.0
Name: fitbit-conf
Version: 0.1
Summary: fitbit configuration tasks
Home-page: www.fitbit.com
Author: Igor Kuplevich
Author-email: ikuplevich@fitbit.com
License: UNKNOWN
Keywords: fitbit,configuration
Platform: any
